CHANGES.txt
MANIFEST.in
README.txt
setup.py
collective/__init__.py
collective.local.adduser.egg-info/PKG-INFO
collective.local.adduser.egg-info/SOURCES.txt
collective.local.adduser.egg-info/dependency_links.txt
collective.local.adduser.egg-info/entry_points.txt
collective.local.adduser.egg-info/namespace_packages.txt
collective.local.adduser.egg-info/not-zip-safe
collective.local.adduser.egg-info/requires.txt
collective.local.adduser.egg-info/top_level.txt
collective/local/__init__.py
collective/local/adduser/__init__.py
collective/local/adduser/configure.zcml
collective/local/adduser/dexterity.zcml
collective/local/adduser/event.py
collective/local/adduser/extender.py
collective/local/adduser/interfaces.py
collective/local/adduser/minimal.zcml
collective/local/adduser/minimal_wo_roles.zcml
collective/local/adduser/vocabulary.py
collective/local/adduser/locales/adduser-manual.pot
collective/local/adduser/locales/adduser.pot
collective/local/adduser/locales/update.sh
collective/local/adduser/locales/de/LC_MESSAGES/adduser.po
collective/local/adduser/locales/fr/LC_MESSAGES/adduser.po
collective/local/adduser/tests/__init__.py
collective/local/adduser/tests/test_newuser.py