Metadata-Version: 1.1
Name: collective.local.adduser
Version: 1.4
Summary: Allows to create a user and assign roles directly from the sharing tab. By Ecreall
Home-page: http://svn.plone.org/svn/collective/collective.local.adduser
Author: Vincent Fretin
Author-email: vincent.fretin@gmail.com
License: GPL
Platform: UNKNOWN
Classifier: Framework :: Plone
Classifier: Programming Language :: Python
